.VERSION
AUTHORS.rst
CONTRIBUTING.rst
HISTORY.rst
LICENSE
MANIFEST.in
Pipfile
Pipfile.lock
README.rst
USAGE.rst
dev-requirements.txt
requirements.txt
setup.cfg
setup.py
docs/Makefile
docs/authors.rst
docs/conf.py
docs/contributing.rst
docs/history.rst
docs/index.rst
docs/installation.rst
docs/readme.rst
docs/usage.rst
tests/test_wikiseriesevilib.py
wikiseriesevilib/.VERSION
wikiseriesevilib/AUTHORS.rst
wikiseriesevilib/CONTRIBUTING.rst
wikiseriesevilib/HISTORY.rst
wikiseriesevilib/LICENSE
wikiseriesevilib/Pipfile
wikiseriesevilib/Pipfile.lock
wikiseriesevilib/README.rst
wikiseriesevilib/USAGE.rst
wikiseriesevilib/__init__.py
wikiseriesevilib/_version.py
wikiseriesevilib/dev-requirements.txt
wikiseriesevilib/requirements.txt
wikiseriesevilib/wikiseriesevilib.py
wikiseriesevilib/wikiseriesevilibexceptions.py
wikiseriesevilib.egg-info/PKG-INFO
wikiseriesevilib.egg-info/SOURCES.txt
wikiseriesevilib.egg-info/dependency_links.txt
wikiseriesevilib.egg-info/not-zip-safe
wikiseriesevilib.egg-info/requires.txt
wikiseriesevilib.egg-info/top_level.txt