Metadata-Version: 2.1
Name: wikiseriesevilib
Version: 0.1.0
Summary: Library to use Wikipedia to query tv series episodes lists
Home-page: https://github.com/evanme20/wikiseriesevilib
Author: Evi Vanmechelen
Author-email: evi_github@gmail.com
License: MIT
Keywords: wikiseriesevilib wikipedia
Classifier: Development Status :: 2 - Pre-Alpha
Classifier: Intended Audience :: Developers
Classifier: License :: OSI Approved :: MIT License
Classifier: Natural Language :: English
Classifier: Programming Language :: Python :: 3.9
License-File: LICENSE
License-File: AUTHORS.rst
